PyMPDATA_examples/__init__.py
PyMPDATA_examples/Arabas_and_Farhat_2020/Bjerksund_and_Stensland_1993.py
PyMPDATA_examples/Arabas_and_Farhat_2020/Black_Scholes_1973.py
PyMPDATA_examples/Arabas_and_Farhat_2020/__init__.py
PyMPDATA_examples/Arabas_and_Farhat_2020/analysis_figures_2_and_3.py
PyMPDATA_examples/Arabas_and_Farhat_2020/analysis_table_1.py
PyMPDATA_examples/Arabas_and_Farhat_2020/colors.py
PyMPDATA_examples/Arabas_and_Farhat_2020/options.py
PyMPDATA_examples/Arabas_and_Farhat_2020/setup1_european_corridor.py
PyMPDATA_examples/Arabas_and_Farhat_2020/setup2_american_put.py
PyMPDATA_examples/Arabas_and_Farhat_2020/simulation.py
PyMPDATA_examples/Bartman_et_al_2022/__init__.py
PyMPDATA_examples/DPDC/__init__.py
PyMPDATA_examples/Jarecka_et_al_2015/__init__.py
PyMPDATA_examples/Jarecka_et_al_2015/formulae.py
PyMPDATA_examples/Jarecka_et_al_2015/plot_output.py
PyMPDATA_examples/Jarecka_et_al_2015/settings.py
PyMPDATA_examples/Jarecka_et_al_2015/simulation.py
PyMPDATA_examples/Jaruga_et_al_2015/__init__.py
PyMPDATA_examples/Magnuszewski_et_al_2025/__init__.py
PyMPDATA_examples/Magnuszewski_et_al_2025/asian_option.py
PyMPDATA_examples/Magnuszewski_et_al_2025/barraquand_data.py
PyMPDATA_examples/Magnuszewski_et_al_2025/common.py
PyMPDATA_examples/Magnuszewski_et_al_2025/monte_carlo.py
PyMPDATA_examples/Molenkamp_test_as_in_Jaruga_et_al_2015_Fig_12/__init__.py
PyMPDATA_examples/Molenkamp_test_as_in_Jaruga_et_al_2015_Fig_12/analysis.py
PyMPDATA_examples/Molenkamp_test_as_in_Jaruga_et_al_2015_Fig_12/settings.py
PyMPDATA_examples/Molenkamp_test_as_in_Jaruga_et_al_2015_Fig_12/simulation.py
PyMPDATA_examples/Olesik_et_al_2022/East_and_Marshall_1954.py
PyMPDATA_examples/Olesik_et_al_2022/README.md
PyMPDATA_examples/Olesik_et_al_2022/__init__.py
PyMPDATA_examples/Olesik_et_al_2022/analysis.py
PyMPDATA_examples/Olesik_et_al_2022/coordinates.py
PyMPDATA_examples/Olesik_et_al_2022/equilibrium_drop_growth.py
PyMPDATA_examples/Olesik_et_al_2022/plotter.py
pympdata_examples-1.6.3.dist-info/METADATA
pympdata_examples-1.6.3.dist-info/WHEEL
pympdata_examples-1.6.3.dist-info/top_level.txt
pympdata_examples-1.6.3.dist-info/RECORD
