Metadata-Version: 2.4
Name: pympdata-examples
Version: 1.6.3
Summary: PyMPDATA usage examples reproducing results from literature and depicting how to use PyMPDATA in Python from Jupyter notebooks
Author: https://github.com/open-atmos/PyMPDATA/graphs/contributors
License: GPL-3.0
Project-URL: Tracker, https://github.com/open-atmos/PyMPDATA/issues
Project-URL: Documentation, https://open-atmos.github.io/PyMPDATA
Project-URL: Source, https://github.com/open-atmos/PyMPDATA
Requires-Dist: PyMPDATA
Requires-Dist: open-atmos-jupyter-utils
Requires-Dist: pystrict
Requires-Dist: matplotlib
Requires-Dist: scipy
Requires-Dist: pint
Requires-Dist: joblib
Requires-Dist: sympy
Requires-Dist: imageio
Requires-Dist: meshio
Requires-Dist: numdifftools
Requires-Dist: pandas
Dynamic: author
Dynamic: description
Dynamic: description-content-type
Dynamic: license
Dynamic: project-url
Dynamic: requires-dist
Dynamic: summary
